tf_init_booster/__init__.py
tf_init_booster/booster.py
tf_init_booster-1.1.0.dist-info/METADATA
tf_init_booster-1.1.0.dist-info/WHEEL
tf_init_booster-1.1.0.dist-info/entry_points.txt
tf_init_booster-1.1.0.dist-info/top_level.txt
tf_init_booster-1.1.0.dist-info/RECORD
