Metadata-Version: 2.1
Name: tf-init-booster
Version: 1.1.0
Summary: terraform init booster
Home-page: UNKNOWN
Author: Alex Khaerov
License: UNKNOWN
Platform: UNKNOWN
Classifier: Programming Language :: Python :: 3
Classifier: License :: OSI Approved :: MIT License
Classifier: Operating System :: OS Independent
Requires-Python: >=3.6
